README.md
setup.py
barwex_vscodews/__init__.py
barwex_vscodews/barwexutils.py
barwex_vscodews/main.py
barwex_vscodews.egg-info/PKG-INFO
barwex_vscodews.egg-info/SOURCES.txt
barwex_vscodews.egg-info/dependency_links.txt
barwex_vscodews.egg-info/entry_points.txt
barwex_vscodews.egg-info/top_level.txt