Metadata-Version: 2.1
Name: barwex-vscodews
Version: 0.2
Summary: Create desktop shortcuts for vscode workspace
Author: barwe
Author-email: barwechin@163.com
